{"name":"Borgaralaun","tagline":"Málefnahópur Pírata um borgaralaun","body":"## Hvað er þetta?\r\n\r\nÞetta er vefsíða málefnahóps Pírata um borgaralaun. Hér má finna upplýsingar um stöðu vinnunnar, tengla í ýmsar upplýsingar um málin sem við erum að skoða, og annað af því tagi. Eftir því sem fram líður verður hægt að finna uppkast að skýrslu hópsins hér.\r\n\r\n## Og upp á íslensku?\r\n\r\nPíratar hafa frá upphafi haft áhuga á því að breyta með róttækum hætti almannatryggingakerfinu, með það að sjónarmiði að gera það, tjah, _almennt_. Borgaralaun eru nafn fyrir þá hugmynd: Allir fá tryggar tekjur. Málefnahópur Pírata er svo stofnaður þegar til stendur að skoða eitthvað ákveðið mál ítarlega. Markmið hópsins er að kanna hvort og hvernig er skynsamlegast að reyna að útfæra borgaralaun á Íslandi, og leggja mat á ýmsum möguleikum fyrir dóm allra pírata. Hugsanlega munum við líka leggja til ákveðna stefnu í málinu. En við tökum ekki endanlega ákvörðun. Okkar hlutverk er að safna og miðla upplýsingum.","google":"","note":"Don't delete this file! It's used internally to help with page regeneration."}